Tool.py
Tool2.py
chengyiLib/__init__.py
chengyiLib/test.py
chengyiLib2/__init__.py
chengyiLib2/test2.py
chengyiLib-1.0.0.dist-info/LICENSE
chengyiLib-1.0.0.dist-info/METADATA
chengyiLib-1.0.0.dist-info/WHEEL
chengyiLib-1.0.0.dist-info/top_level.txt
chengyiLib-1.0.0.dist-info/RECORD
