Metadata-Version: 2.1
Name: chengyiLib
Version: 1.0.0
Summary: this is a chengyi test .py file
Author: spiderMan_007
Author-email: 17888841257@163.com
License-File: LICENSE
